odoo10_addon_product_profile-10.0.1.0.1-nspkg.pth
odoo/addons/product_profile/README.rst
odoo/addons/product_profile/__init__.py
odoo/addons/product_profile/__manifest__.py
odoo/addons/product_profile/demo/product.profile.csv
odoo/addons/product_profile/i18n/ca.po
odoo/addons/product_profile/i18n/de.po
odoo/addons/product_profile/i18n/es.po
odoo/addons/product_profile/i18n/fr.po
odoo/addons/product_profile/i18n/hr.po
odoo/addons/product_profile/i18n/it.po
odoo/addons/product_profile/i18n/nl_NL.po
odoo/addons/product_profile/i18n/product_profile.pot
odoo/addons/product_profile/i18n/sl.po
odoo/addons/product_profile/models/__init__.py
odoo/addons/product_profile/models/config.py
odoo/addons/product_profile/models/product.py
odoo/addons/product_profile/security/group.xml
odoo/addons/product_profile/security/ir.model.access.csv
odoo/addons/product_profile/static/description/akretion.png
odoo/addons/product_profile/static/description/c1.png
odoo/addons/product_profile/static/description/c2.png
odoo/addons/product_profile/static/description/c3.png
odoo/addons/product_profile/static/description/field.png
odoo/addons/product_profile/static/description/icon.png
odoo/addons/product_profile/static/description/index.html
odoo/addons/product_profile/static/description/list.png
odoo/addons/product_profile/static/description/prof_warning.png
odoo/addons/product_profile/views/config_view.xml
odoo/addons/product_profile/views/product_view.xml
odoo10_addon_product_profile-10.0.1.0.1.dist-info/METADATA
odoo10_addon_product_profile-10.0.1.0.1.dist-info/WHEEL
odoo10_addon_product_profile-10.0.1.0.1.dist-info/namespace_packages.txt
odoo10_addon_product_profile-10.0.1.0.1.dist-info/top_level.txt
odoo10_addon_product_profile-10.0.1.0.1.dist-info/RECORD
